cliologging/__init__.py
cliologging/logger.py
cliologging-1.0.0.dist-info/METADATA
cliologging-1.0.0.dist-info/WHEEL
cliologging-1.0.0.dist-info/top_level.txt
cliologging-1.0.0.dist-info/RECORD
