Metadata-Version: 2.1
Name: cliologging
Version: 1.0.0
Summary: Add-on to the official Python logging library.
Home-page: UNKNOWN
Author: Julien BALDERIOTTI
License: UNKNOWN
Platform: UNKNOWN
